LICENSE.txt
MANIFEST.in
README.md
setup.cfg
setup.py
letsencrypt_pritunl.egg-info/PKG-INFO
letsencrypt_pritunl.egg-info/SOURCES.txt
letsencrypt_pritunl.egg-info/dependency_links.txt
letsencrypt_pritunl.egg-info/entry_points.txt
letsencrypt_pritunl.egg-info/requires.txt
letsencrypt_pritunl.egg-info/top_level.txt
pritunl_plugin/__init__.py
pritunl_plugin/pritunl.py