Metadata-Version: 1.1
Name: letsencrypt-pritunl
Version: 0.1.3
Summary: Pritunl plugin for Let's Encrypt client
Home-page: https://github.com/kharkevich/letsencrypt-pritunl
Author: Aliaksandr Kharkevich
Author-email: aliaksandr_kharkevich@outlook.com
License: Apache License 2.0
Download-URL: https://github.com/kharkevich/letsencrypt-pritunl/archive/0.1.3.tar.gz
Keywords: letsencrypt,pritunl
Platform: any
Classifier: Development Status :: 3 - Alpha
Classifier: Topic :: Utilities
Classifier: License :: OSI Approved :: Apache Software License
